comfydock/__init__.py
comfydock/cli.py
comfydock/cli_defaults.json
comfydock/commands/__init__.py
comfydock/commands/config.py
comfydock/commands/dev.py
comfydock/commands/server.py
comfydock/commands/update.py
comfydock/core/__init__.py
comfydock/core/config.py
comfydock/core/logging.py
comfydock/core/updates.py
comfydock/utils/__init__.py
comfydock/utils/helpers.py
comfydock-0.3.3.dist-info/METADATA
comfydock-0.3.3.dist-info/WHEEL
comfydock-0.3.3.dist-info/entry_points.txt
comfydock-0.3.3.dist-info/RECORD
