Metadata-Version: 2.4
Name: comfydock
Version: 0.3.3
Summary: ComfyDock CLI
Requires-Python: >=3.12
Requires-Dist: click>=8.1.8
Requires-Dist: comfydock-server>=0.3.2
Requires-Dist: packaging>=24.2
Requires-Dist: pydantic>=2.10.6
Requires-Dist: python-dotenv>=1.0.1
Requires-Dist: setuptools>=80.9.0
